cuda_selector/__init__.py
cuda_selector/cuda.py
cuda_selector-0.1.5.dist-info/METADATA
cuda_selector-0.1.5.dist-info/WHEEL
cuda_selector-0.1.5.dist-info/top_level.txt
cuda_selector-0.1.5.dist-info/RECORD
